PyWin32.chm
pythoncom.py
pywin32.pth
pywin32.version.txt
adodbapi/__init__.py
adodbapi/ado_consts.py
adodbapi/adodbapi.py
adodbapi/apibase.py
adodbapi/is64bit.py
adodbapi/license.txt
adodbapi/process_connect_string.py
adodbapi/readme.txt
adodbapi/schema_table.py
adodbapi/setup.py
adodbapi/examples/db_print.py
adodbapi/examples/db_table_names.py
adodbapi/examples/xls_read.py
adodbapi/examples/xls_write.py
adodbapi/test/adodbapitest.py
adodbapi/test/adodbapitestconfig.py
adodbapi/test/dbapi20.py
adodbapi/test/is64bit.py
adodbapi/test/setuptestframework.py
adodbapi/test/test_adodbapi_dbapi20.py
adodbapi/test/tryconnection.py
isapi/PyISAPI_loader.dll
isapi/README.txt
isapi/__init__.py
isapi/install.py
isapi/isapicon.py
isapi/simple.py
isapi/threaded_extension.py
isapi/doc/isapi.html
isapi/samples/README.txt
isapi/samples/advanced.py
isapi/samples/redirector.py
isapi/samples/redirector_asynch.py
isapi/samples/redirector_with_filter.py
isapi/samples/test.py
isapi/test/README.txt
isapi/test/extension_simple.py
pythonwin/Pythonwin.exe
pythonwin/dde.pyd
pythonwin/license.txt
pythonwin/mfc140u.dll
pythonwin/scintilla.dll
pythonwin/start_pythonwin.pyw
pythonwin/win32ui.pyd
pythonwin/win32uiole.pyd
pythonwin/pywin/IDLE.cfg
pythonwin/pywin/__init__.py
pythonwin/pywin/default.cfg
pythonwin/pywin/Demos/cmdserver.py
pythonwin/pywin/Demos/createwin.py
pythonwin/pywin/Demos/demoutils.py
pythonwin/pywin/Demos/dibdemo.py
pythonwin/pywin/Demos/dlgtest.py
pythonwin/pywin/Demos/dyndlg.py
pythonwin/pywin/Demos/fontdemo.py
pythonwin/pywin/Demos/guidemo.py
pythonwin/pywin/Demos/hiertest.py
pythonwin/pywin/Demos/menutest.py
pythonwin/pywin/Demos/objdoc.py
pythonwin/pywin/Demos/openGLDemo.py
pythonwin/pywin/Demos/progressbar.py
pythonwin/pywin/Demos/sliderdemo.py
pythonwin/pywin/Demos/splittst.py
pythonwin/pywin/Demos/threadedgui.py
pythonwin/pywin/Demos/toolbar.py
pythonwin/pywin/Demos/app/basictimerapp.py
pythonwin/pywin/Demos/app/customprint.py
pythonwin/pywin/Demos/app/demoutils.py
pywin32-310.dist-info/METADATA
pywin32-310.dist-info/WHEEL
pywin32-310.dist-info/entry_points.txt
pywin32-310.dist-info/top_level.txt
pywin32-310.dist-info/RECORD
